canedge_browser/FuncBackedList.py
canedge_browser/__init__.py
canedge_browser/_version.py
canedge_browser/config.py
canedge_browser/listing.py
canedge_browser/support/AbstractFileSystemWithBucket.py
canedge_browser/support/FuncBackedList.py
canedge_browser/support/LocalFileSystem.py
canedge_browser/support/RelativeFileSystem.py
canedge_browser/support/__init__.py
canedge_browser-0.0.8.dist-info/LICENSE
canedge_browser-0.0.8.dist-info/METADATA
canedge_browser-0.0.8.dist-info/WHEEL
canedge_browser-0.0.8.dist-info/top_level.txt
canedge_browser-0.0.8.dist-info/RECORD
