Metadata-Version: 2.1
Name: canedge-browser
Version: 0.0.8
Summary: Utilities to list log files generated by CANedge loggers
Home-page: https://github.com/CSS-Electronics/canedge_browser
Author: Magnus Aagaard Sørensen
Author-email: mas@csselectronics.com
License: UNKNOWN
Platform: UNKNOWN
Classifier: License :: OSI Approved :: MIT License
Classifier: Development Status :: 3 - Alpha
Classifier: Operating System :: OS Independent
Classifier: Programming Language :: Python :: 3.5
Classifier: Programming Language :: Python :: 3.6
Classifier: Programming Language :: Python :: 3.7
Classifier: Programming Language :: Python :: 3.8
Requires-Python: >=3.5
License-File: LICENSE
Requires-Dist: fsspec
Requires-Dist: mdf-iter
